action_network/__init__.py
action_network/action_network.py
action_network/models/__init__.py
action_network/models/advocacy_campaigns/__init__.py
action_network/models/advocacy_campaigns/advocacy_campaign.py
action_network/models/advocacy_campaigns/advocacy_campaigns.py
action_network/models/attendances/__init__.py
action_network/models/attendances/attendance.py
action_network/models/attendances/attendances.py
action_network/models/campaigns/__init__.py
action_network/models/campaigns/campaign.py
action_network/models/campaigns/campaigns.py
action_network/models/custom_fields/__init__.py
action_network/models/custom_fields/custom_fields.py
action_network/models/donations/__init__.py
action_network/models/donations/donation.py
action_network/models/donations/donations.py
action_network/models/embed/__init__.py
action_network/models/embed/embed.py
action_network/models/event_campaigns/__init__.py
action_network/models/event_campaigns/event_campaign.py
action_network/models/event_campaigns/event_campaigns.py
action_network/models/events/__init__.py
action_network/models/events/event.py
action_network/models/events/events.py
action_network/models/forms/__init__.py
action_network/models/forms/form.py
action_network/models/forms/forms.py
action_network/models/fundraising_pages/__init__.py
action_network/models/fundraising_pages/fundraising_page.py
action_network/models/fundraising_pages/fundraising_pages.py
action_network/models/items/__init__.py
action_network/models/items/item.py
action_network/models/items/items.py
action_network/models/lists/__init__.py
action_network/models/lists/list.py
action_network/models/lists/lists.py
action_network/models/messages/__init__.py
action_network/models/messages/message.py
action_network/models/messages/messages.py
action_network/models/metadata/__init__.py
action_network/models/metadata/metadata.py
action_network/models/outreaches/__init__.py
action_network/models/outreaches/outreach.py
py_actionnetworkorg-1.1.9.dist-info/LICENSE
py_actionnetworkorg-1.1.9.dist-info/METADATA
py_actionnetworkorg-1.1.9.dist-info/WHEEL
py_actionnetworkorg-1.1.9.dist-info/top_level.txt
py_actionnetworkorg-1.1.9.dist-info/RECORD
