Metadata-Version: 2.1
Name: py-actionnetworkorg
Version: 1.1.9
Summary: Unofficial python package for ActionNetwork (https://actionnetwork.org/)
Home-page: https://github.com/NirTatcher/actionnetworkpy.git
Author: Nir Tatcher
Author-email: <nirto111@gmail.com>
License: UNKNOWN
Keywords: python,action_network,ActionNetwork,actionnetwork,AN,an
Platform: UNKNOWN
Classifier: Programming Language :: Python :: 3
Classifier: License :: OSI Approved :: MIT License
Classifier: Operating System :: OS Independent
Requires-Python: >=3.6
License-File: LICENSE
Requires-Dist: psycopg2-binary (==2.9.6)
Requires-Dist: Requests (==2.31.0)
Requires-Dist: setuptools (==65.5.0)
Requires-Dist: sshtunnel (==0.4.0)
